setup.py
src/__init__.py
src/configParser.py
src/torrent_info.py
src/zflix.py
src/subtitle/__init__.py
src/subtitle/opensubtitle.py
src/subtitle/subtitle.py
src/trackers/__init__.py
src/trackers/kat.py
src/trackers/torrentz.py
test/testTorrentz.py
zflix.egg-info/PKG-INFO
zflix.egg-info/SOURCES.txt
zflix.egg-info/dependency_links.txt
zflix.egg-info/top_level.txt