Metadata-Version: 1.1
Name: zflix
Version: 0.31
Summary: Script that seek and play torrent
Home-page: https://github.com/thomacer/zflix
Author: PERALE Thomas
Author-email: thomas.perale@openmailbox.org
License: GPL V3
Platform: UNKNOWN
Classifier: Environment :: Console
Classifier: Operating System :: POSIX :: Linux
Classifier: Programming Language :: Python
Classifier: Topic :: Multimedia :: Video
